levox/__init__.py
levox/advanced_scanner.py
levox/ai_context_engine.py
levox/benchmark.py
levox/business.py
levox/cli.py
levox/cli_pro.py
levox/config.py
levox/data_flow_analyzer.py
levox/fixer.py
levox/frameworks.py
levox/gdpr_articles.py
levox/hybrid_orchestrator.py
levox/license_manager.py
levox/main.py
levox/meta_learning.py
levox/remediation_module.py
levox/report.py
levox/rule_scanner.py
levox/scanner.py
levox-1.5.4.dist-info/LICENSE
levox-1.5.4.dist-info/METADATA
levox-1.5.4.dist-info/WHEEL
levox-1.5.4.dist-info/entry_points.txt
levox-1.5.4.dist-info/top_level.txt
levox-1.5.4.dist-info/RECORD
