Metadata-Version: 2.2
Name: levox
Version: 1.5.4
Summary: GDPR, PII and Data Flow Compliance Tool
Home-page: https://github.com/levox/gdpr-compliance
Author: Levox Team
Author-email: info@levox.io
Keywords: gdpr,compliance,security,privacy,pii,data-protection
Classifier: Development Status :: 4 - Beta
Classifier: Intended Audience :: Developers
Classifier: Topic :: Software Development :: Quality Assurance
Classifier: Topic :: Security
Classifier: Programming Language :: Python :: 3
Classifier: Programming Language :: Python :: 3.7
Classifier: Programming Language :: Python :: 3.8
Classifier: Programming Language :: Python :: 3.9
Classifier: Programming Language :: Python :: 3.10
Classifier: License :: OSI Approved :: MIT License
Requires-Python: >=3.7
License-File: LICENSE
Requires-Dist: prompt_toolkit>=3.0.0
Requires-Dist: ollama>=0.1.0
Requires-Dist: regex>=2023.0.0
Requires-Dist: pyyaml>=6.0.0
Requires-Dist: rich>=13.0.0
Requires-Dist: tqdm>=4.65.0
Requires-Dist: watchdog>=3.0.0
Requires-Dist: matplotlib>=3.5.0
Requires-Dist: numpy>=1.20.0
Requires-Dist: weasyprint>=53.0
Requires-Dist: apscheduler>=3.9.0
Requires-Dist: requests>=2.27.0
Dynamic: author
Dynamic: author-email
Dynamic: classifier
Dynamic: description
Dynamic: description-content-type
Dynamic: home-page
Dynamic: keywords
Dynamic: requires-dist
Dynamic: requires-python
Dynamic: summary
